firezone_client/__init__.py
firezone_client/key_generator.py
firezone_client/models/Configuration.py
firezone_client/models/Device.py
firezone_client/models/Rule.py
firezone_client/models/User.py
firezone_client/models/__init__.py
firezone_client/password_generator.py
firezone_client-0.1.1.dist-info/METADATA
firezone_client-0.1.1.dist-info/WHEEL
firezone_client-0.1.1.dist-info/RECORD
