Metadata-Version: 2.1
Name: firezone-client
Version: 0.1.1
Summary: Client for firezone
Author: msterhuj
Author-email: gabin.lanore@gmail.com
Requires-Python: >=3.11,<4.0
Classifier: Programming Language :: Python :: 3
Classifier: Programming Language :: Python :: 3.11
Classifier: Programming Language :: Python :: 3.12
Classifier: Programming Language :: Python :: 3.13
Requires-Dist: cryptography (>=43.0.3,<44.0.0)
Requires-Dist: requests (>=2.31.0,<3.0.0)
